{
  "uri": "null",
  "publishedDate": "2015-06-23T00:00:00Z",
  "publisher": {
    "scheme": "GACM",
    "uid": null,
    "name": "Grupo Aeroportuario de la Ciudad de México",
    "uri": "http://www.aeropuerto.gob.mx/gacm/index.php"
  },
  "releases": [
    {
      "language": "es",
      "ocid": "LO-009KDH999-N47-2015",
      "id": "LO-009KDH999-N47-2015",
      "date": "2015-06-23T00:00:00Z",
      "tag": [
        "Contrato"
      ],
      "initiationType": "tender",
      "buyer": {
        "identifier": {
          "scheme": "GACM",
          "id": null,
          "legalName": "Grupo Aeroportuario de la Ciudad de México",
          "uri": "http://www.aeropuerto.gob.mx/gacm/index.php"
        },
        "name": "Grupo Aeroportuario de la Ciudad de México",
        "address": {
          "locality": "Ciudad de México",
          "region": "Ciudad de México",
          "countryName": "México"
        },
        "contactPoint": {
          "name": null
        }
      },
      "awards": [
        {
          "id": "LO-009KDH999- N47-2015",
          "title": "Acta de emisión de fallo ",
          "description": "Con fundamento en lo dispuesto en el artículo 39, fracción III de la LOPSRM, se adjudica el contrato al consorcio integrado por Acciones Grupo Oro, S.A. de C.V. y Constructora Grupo de Oro, S.A. de C.V. , por un importe de $112,046,320.57, monto sin considerar el IVA, por resultar se la propuesta que al ser evaluada técnica y ecómicamente, obtuvo el puntaje más alto acorde al mecanismo de evaluación previsto en la convocatoria. ",
          "status": "Adjudicado ",
          "date": "2015-08-28T00:00:00Z",
          "value": {
            "amount": 112046320.57,
            "currency": "MNX"
          },
          "suppliers": [
            {
              "identifier": {
                "scheme": null,
                "id": "1. Acciones Grupo Oro, S.A. de C.V.  AGO090512QT4 2.Constructora Grupo de Oro, S.A. de C.V. CGO060731P72",
                "legalName": "1. Acciones Grupo Oro, S.A. de C.V.  2.Constructora Grupo de Oro, S.A. de C.V.",
                "uri": "http://www.grupodeoro.com.mx/consulta_empresa.php?empresas=12"
              },
              "additionalIdentifiers": [
                {
                  "scheme": null,
                  "id": null
                }
              ],
              "name": "1. Acciones Grupo Oro, S.A. de C.V.  2.Constructora Grupo de Oro, S.A. de C.V.",
              "address": {
                "streetAddress": "Prolongación 18 de marzo 300",
                "locality": "Morelia",
                "region": "Michoacán",
                "postalCode": "58080",
                "countryName": "México"
              },
              "contactPoint": {
                "name": "Ricardo Ramos Acosta",
                "email": null,
                "telephone": null,
                "faxNumber": null
              }
            }
          ],
          "items": [
            {
              "id": "62501001",
              "description": "Construcción aeropista",
              "classification": {
                "scheme": null,
                "id": null,
                "description": "Obra pública",
                "uri": null
              },
              "additionalClassifications": [
                {
                  "scheme": null,
                  "id": null,
                  "description": null,
                  "uri": null
                }
              ],
              "quantity": 1,
              "unit": {
                "name": "Obra",
                "value": {
                  "amount": null,
                  "currency": "MXN"
                }
              }
            }
          ],
          "contractPeriod": {
            "startDate": "2015-09-10T00:00:00Z",
            "endDate": "2016-06-04T00:00:00Z"
          },
          "documents": [
            {
              "id": "LO-009KDH999- N47-2015",
              "documentType": null,
              "title": "Acta de emisión de fallo ",
              "description": "Con fundamento en lo dispuesto en el artículo 39, fracción III de la LOPSRM, se adjudica el contrato al consorcio integrado por Acciones Grupo Oro, S.A. de C.V. y Constructora Grupo de Oro, S.A. de C.V. , por un importe de $112,046,320.57, monto sin considerar el IVA, por resultar se la propuesta que al ser evaluada técnica y ecómicamente, obtuvo el puntaje más alto acorde al mecanismo de evaluación previsto en la convocatoria. ",
              "url": null,
              "datePublished": null,
              "format": null,
              "language": "es"
            }
          ]
        }
      ],
      "contracts": [
        {
          "id": "LPN-OP-DCAGI-SC-066/15",
          "awardID": "LO-009KDH999- N47-2015",
          "title": "Desarrollo del Proyecto Ejecutivo, construcción, equipamiento de mobiliario en instalaciones complementarias para el campamento del Grupo Aeroportuario de la Ciudad de México en el sitio del Nuevo Aeropuerto Internacional de la Ciudad de México.",
          "description": null,
          "status": "Activo",
          "period": {
            "startDate": "2015-09-10T00:00:00Z",
            "endDate": "2016-04-06T00:00:00Z"
          },
          "value": {
            "amount": 112046320.57,
            "currency": "MXN"
          },
          "items": [
            {
              "id": "null",
              "description": null,
              "classification": {
                "scheme": null,
                "id": null,
                "description": null,
                "uri": null
              }
            }
          ],
          "additionalClassifications": [
            {
              "scheme": null,
              "id": null,
              "description": null,
              "uri": null
            }
          ],
          "quantity": null,
          "unit": {
            "name": "Obra",
            "value": {
              "amount": null,
              "currency": "MXN"
            }
          },
          "dateSigned": "2015-09-10T00:00:00Z",
          "documents": [
            {
              "id": "1188539",
              "documentType": "contractSigned",
              "title": "Contrato plurianual de obra pública a precio alzado  número LPN-OP-DCAGI-SC-066/15",
              "description": null,
              "url": "/datos_abiertos/pdf/Campamento/LO-009KDH999-N47-2015_Contrato.pdf",
              "datePublished": null,
              "format": null,
              "language": "es"
            }
          ]
        }
      ]
    }
  ]
}
